{
  "field": "reg",
  "map": [
    {
      "AG": "AG"
    },
    {
      "ALLEMAGNE": "DE"
    },
    {
      "AN": "AN"
    },
    {
      "ARGENTINA": "AR"
    },
    {
      "AU": "AU"
    },
    {
      "AUSTRALIA": "AU"
    },
    {
      "BAHAMAS": "BS"
    },
    {
      "BB": "BB"
    },
    {
      "BE": "BE"
    },
    {
      "BELGIUM": "BE"
    },
    {
      "BERIA": "MZ"
    },
    {
      "BERMUDA": "BM"
    },
    {
      "BM": "BM"
    },
    {
      "BRASIL": "BR"
    },
    {
      "BRAZIL": "BR"
    },
    {
      "BRAZILIA": "BR"
    },
    {
      "BRIT.": "GB"
    },
    {
      "BRITISH": "GB"
    },
    {
      "BS": "BS"
    },
    {
      "BULGARIA": "BG"
    },
    {
      "BURMA": "MM"
    },
    {
      "BZ": "BZ"
    },
    {
      "CA": "CA"
    },
    {
      "CH": "CH"
    },
    {
      "CHILE": "CL"
    },
    {
      "CHILI": "CL"
    },
    {
      "CHINA": "CN"
    },
    {
      "CHINESE": "CN"
    },
    {
      "CK": "CK"
    },
    {
      "CN": "CN"
    },
    {
      "COLOMBIA": "CO"
    },
    {
      "COLUMBIA": "CO"
    },
    {
      "CONGO": "CG"
    },
    {
      "COREA LIBERIA": "LR"
    },
    {
      "COSTA RICA": "CR"
    },
    {
      "CUBA": "CU"
    },
    {
      "CY": "CY"
    },
    {
      "CYPRUS": "CY"
    },
    {
      "CZECHOSLOVAKIA": "CZ"
    },
    {
      "D.R. CONGO": "CD"
    },
    {
      "DAN": "DK"
    },
    {
      "DE": "DE"
    },
    {
      "DENMARK": "DK"
    },
    {
      "DK": "DK"
    },
    {
      "DM": "DM"
    },
    {
      "DUTCH": "NE"
    },
    {
      "EC": "EC"
    },
    {
      "ECUADOR": "EC"
    },
    {
      "ES": "ES"
    },
    {
      "FIJI": "FJ"
    },
    {
      "FIJI ISLANDS": "FJ"
    },
    {
      "FINLAND": "FI"
    },
    {
      "FK": "FK"
    },
    {
      "FO": "FO"
    },
    {
      "FORMOSA": "TW"
    },
    {
      "FR": "FR"
    },
    {
      "FRANCE": "GR"
    },
    {
      "GB": "GB"
    },
    {
      "GER": "DE"
    },
    {
      "GERMAN": "DE"
    },
    {
      "GERMANY": "DE"
    },
    {
      "GHANA": "GH"
    },
    {
      "GI": "GI"
    },
    {
      "GL": "GL"
    },
    {
      "GLASCOW SCOTL.": "GB"
    },
    {
      "GR": "GR"
    },
    {
      "GREAT BRITAIN": "GB"
    },
    {
      "GREECE": "GR"
    },
    {
      "GUINEA": "GN"
    },
    {
      "HK": "HK"
    },
    {
      "HONDURAS": "HN"
    },
    {
      "HONG KONG": "HK"
    },
    {
      "ID": "ID"
    },
    {
      "IE": "IE"
    },
    {
      "IL": "IL"
    },
    {
      "IM": "IM"
    },
    {
      "IN": "IN"
    },
    {
      "INDIA": "IN"
    },
    {
      "INDIAN": "IN"
    },
    {
      "INDONESIA": "ID"
    },
    {
      "IRELAND": "IE"
    },
    {
      "ISRAEL": "IL"
    },
    {
      "ISRAELI": "IL"
    },
    {
      "IT": "IT"
    },
    {
      "ITALIAN": "IT"
    },
    {
      "ITALY": "IT"
    },
    {
      "JAPAN": "JP"
    },
    {
      "JP": "JP"
    },
    {
      "KOREA": "KR"
    },
    {
      "KR": "KR"
    },
    {
      "KUWAIT": "KW"
    },
    {
      "KW": "KW"
    },
    {
      "KY": "KY"
    },
    {
      "LIB": "LR"
    },
    {
      "LIB.": "LR"
    },
    {
      "LIBERIA": "LR"
    },
    {
      "LIBERIAN": "LR"
    },
    {
      "LONDON": "GB"
    },
    {
      "LR": "LR"
    },
    {
      "LU": "LU"
    },
    {
      "MA": "MA"
    },
    {
      "MALAISIE": "MY"
    },
    {
      "MALAYA": "MY"
    },
    {
      "MALAYSIA": "MY"
    },
    {
      "MALTA": "MT"
    },
    {
      "MB": "MB"
    },
    {
      "MEX": "MX"
    },
    {
      "MEXICO": "MX"
    },
    {
      "MH": "MH"
    },
    {
      "MN": "MN"
    },
    {
      "MOMBASA": "KE"
    },
    {
      "MONROVIA": "LR"
    },
    {
      "MSNG": "NULL"
    },
    {
      "MT": "MT"
    },
    {
      "MY": "MY"
    },
    {
      "NAURU": "NR"
    },
    {
      "NETHERLAND": "NL"
    },
    {
      "NETHERLANDS": "NL"
    },
    {
      "NEW ZEALAND": "NZ"
    },
    {
      "NICARAGUA": "NI"
    },
    {
      "NL": "NL"
    },
    {
      "NO": "NO"
    },
    {
      "NORVEGE": "NO"
    },
    {
      "NORWAY": "NO"
    },
    {
      "NORWEGIAN": "NO"
    },
    {
      "NZ": "NZ"
    },
    {
      "PA": "PA"
    },
    {
      "PAKISTAN": "PK"
    },
    {
      "PANAMA": "PA"
    },
    {
      "PANAMA PANAMA": "PA"
    },
    {
      "PDEP": "PDEP"
    },
    {
      "PERU": "PE"
    },
    {
      "PH": "PH"
    },
    {
      "PHILIPPINES": "PH"
    },
    {
      "PL": "PL"
    },
    {
      "PORTUGAL": "PT"
    },
    {
      "PR": "PR"
    },
    {
      "REP. OF KOREA": "KR"
    },
    {
      "REP.OF KOREA": "KR"
    },
    {
      "REPUBLIC OF KOREA": "KR"
    },
    {
      "RU": "RU"
    },
    {
      "SA": "SA"
    },
    {
      "SCHWEIZ": "CH"
    },
    {
      "SCOTLAND": "GB"
    },
    {
      "SE": "SE"
    },
    {
      "SEYCH.": "SC"
    },
    {
      "SG": "SG"
    },
    {
      "SICILY": "IT"
    },
    {
      "SINGAPORE": "SG"
    },
    {
      "SO": "SO"
    },
    {
      "SOMALI, DEM.REP.": "SO"
    },
    {
      "SOUTH AFRICA": "ZA"
    },
    {
      "SPAIN": "ES"
    },
    {
      "SWEDEN": "SE"
    },
    {
      "SWEDISH": "SE"
    },
    {
      "SWISS": "CH"
    },
    {
      "SWITERLAND": "CH"
    },
    {
      "SWITZERLAND": "CH"
    },
    {
      "SWIZERLAND": "CH"
    },
    {
      "TO": "TO"
    },
    {
      "TR": "TR"
    },
    {
      "TRINIDAD": "TT"
    },
    {
      "TU": "TU"
    },
    {
      "TUNISIE": "TN"
    },
    {
      "TURKEY": "TR"
    },
    {
      "U.K": "GB"
    },
    {
      "U.K.": "GB"
    },
    {
      "U.S.A.": "US"
    },
    {
      "UGANDA": "UG"
    },
    {
      "UK": "GB"
    },
    {
      "UNIT KINGDOM": "GB"
    },
    {
      "UNITED KINGDOM": "GB"
    },
    {
      "US": "US"
    },
    {
      "VC": "VC"
    },
    {
      "VENEZUELA": "VE"
    },
    {
      "VIET NAM": "VN"
    },
    {
      "VIET-NAM": "VN"
    },
    {
      "VOLW": "VOLW"
    },
    {
      "VU": "VU"
    },
    {
      "W. GERMAN": "DE"
    },
    {
      "W.GERMAN": "DE"
    },
    {
      "WS": "WS"
    },
    {
      "YUGOSLAVIA": "YU"
    },
    {
      "ZA": "ZA"
    }
  ]
}
